thumbnails/__init__.py
thumbnails/plugin.py
thumbnails/thumbnail.py
mkdocs_thumbnails-0.0.10.dist-info/LICENSE
mkdocs_thumbnails-0.0.10.dist-info/METADATA
mkdocs_thumbnails-0.0.10.dist-info/WHEEL
mkdocs_thumbnails-0.0.10.dist-info/entry_points.txt
mkdocs_thumbnails-0.0.10.dist-info/top_level.txt
mkdocs_thumbnails-0.0.10.dist-info/RECORD
