Metadata-Version: 2.1
Name: mkdocs-thumbnails
Version: 0.0.10
Summary: An MkDocs plugin.  Generates thumbnails of PDF files and YouTube links.
Home-page: https://github.com/normanlorrain/mkdocs-thumbnails
Author: Norman Lorrain
Author-email: normanlorrain@gmail.com
Project-URL: Bug Tracker, https://github.com/normanlorrain/mkdocs-thumbnails/issues
Classifier: Programming Language :: Python :: 3
Classifier: License :: OSI Approved :: MIT License
Classifier: Operating System :: OS Independent
Requires-Python: >=3.6
License-File: LICENSE
Requires-Dist: pymupdf (>=1.18)
Requires-Dist: mkdocs (>=1.0)
Requires-Dist: Pillow (>=8.0)
Requires-Dist: beautifulsoup4
Requires-Dist: requests-cache
